odoo/addons/delivery_total_weight_from_packaging/README.rst
odoo/addons/delivery_total_weight_from_packaging/__init__.py
odoo/addons/delivery_total_weight_from_packaging/__manifest__.py
odoo/addons/delivery_total_weight_from_packaging/i18n/delivery_total_weight_from_packaging.pot
odoo/addons/delivery_total_weight_from_packaging/models/__init__.py
odoo/addons/delivery_total_weight_from_packaging/models/stock_move.py
odoo/addons/delivery_total_weight_from_packaging/models/stock_picking.py
odoo/addons/delivery_total_weight_from_packaging/models/stock_quant_package.py
odoo/addons/delivery_total_weight_from_packaging/readme/CONTRIBUTORS.rst
odoo/addons/delivery_total_weight_from_packaging/readme/CREDITS.rst
odoo/addons/delivery_total_weight_from_packaging/readme/DESCRIPTION.rst
odoo/addons/delivery_total_weight_from_packaging/static/description/icon.png
odoo/addons/delivery_total_weight_from_packaging/static/description/index.html
odoo/addons/delivery_total_weight_from_packaging/tests/__init__.py
odoo/addons/delivery_total_weight_from_packaging/tests/common.py
odoo/addons/delivery_total_weight_from_packaging/tests/test_choose_delivery_package.py
odoo/addons/delivery_total_weight_from_packaging/tests/test_weight_from_packaging.py
odoo/addons/delivery_total_weight_from_packaging/wizard/__init__.py
odoo/addons/delivery_total_weight_from_packaging/wizard/choose_delivery_package.py
odoo13_addon_delivery_total_weight_from_packaging-13.0.1.1.2.dist-info/METADATA
odoo13_addon_delivery_total_weight_from_packaging-13.0.1.1.2.dist-info/WHEEL
odoo13_addon_delivery_total_weight_from_packaging-13.0.1.1.2.dist-info/top_level.txt
odoo13_addon_delivery_total_weight_from_packaging-13.0.1.1.2.dist-info/RECORD
